angelovich/core/DataStorage.py
angelovich/core/Dispatcher.py
angelovich/core/__init__.py
angelovich_core-0.1.6.dist-info/licenses/LICENSE
angelovich_core-0.1.6.dist-info/METADATA
angelovich_core-0.1.6.dist-info/WHEEL
angelovich_core-0.1.6.dist-info/top_level.txt
angelovich_core-0.1.6.dist-info/RECORD
