Metadata-Version: 2.4
Name: angelovich.core
Version: 0.1.6
Summary: Reusable python code by Angelovich
Author-email: Angelovich <angel777da@gmail.com>
License-Expression: MIT
Project-URL: Homepage, https://github.com/Angel777d/angelovich.core
Project-URL: Changelog, https://github.com/Angel777d/angelovich.core/blob/main/CHANGELOG.md
Keywords: Data Storage,ECS-like,event bus,decouple,
Classifier: Development Status :: 4 - Beta
Classifier: Intended Audience :: Developers
Classifier: Programming Language :: Python :: 3.13
Classifier: Programming Language :: Python :: 3.14
Requires-Python: >=3.13
License-File: LICENSE
Dynamic: license-file
